lddtest/__init__.py
lddtest/dcdensity.py
lddtest/enums.py
lddtest/hartman.py
lddtest/kernel.py
lddtest/lddtest.py
lddtest/utils.py
lddtest-0.1.2.dist-info/LICENSE
lddtest-0.1.2.dist-info/METADATA
lddtest-0.1.2.dist-info/WHEEL
lddtest-0.1.2.dist-info/RECORD
