Metadata-Version: 2.1
Name: lddtest
Version: 0.1.2
Summary: 
Author: leostimpfle
Author-email: leonardstimpfle@icloud.com
Requires-Python: >=3.12,<4.0
Classifier: Programming Language :: Python :: 3
Classifier: Programming Language :: Python :: 3.12
Requires-Dist: numpy (>=2.2.1,<3.0.0)
Requires-Dist: pandas (>=2.2.3,<3.0.0)
Requires-Dist: statsmodels (>=0.14.4,<0.15.0)
